pycontrols/__init__.py
pycontrols-0.0.4.dist-info/LICENSE
pycontrols-0.0.4.dist-info/METADATA
pycontrols-0.0.4.dist-info/WHEEL
pycontrols-0.0.4.dist-info/top_level.txt
pycontrols-0.0.4.dist-info/RECORD
