Metadata-Version: 2.1
Name: pycontrols
Version: 0.0.4
Summary: OS agnostic modules to control the host machine
Author-email: Vignesh Sivanandha Rao <svignesh1793@gmail.com>
License: MIT License
Project-URL: Homepage, https://github.com/thevickypedia/pycontrols
Project-URL: Bug Tracker, https://github.com/thevickypedia/pycontrols/issues
Keywords: system,notification,volume,wifi,console,stdout,workstation
Classifier: License :: OSI Approved :: MIT License
Classifier: Programming Language :: Python :: 3
Classifier: Development Status :: 5 - Production/Stable
Classifier: Operating System :: MacOS :: MacOS X
Classifier: Operating System :: Microsoft :: Windows
Classifier: Operating System :: POSIX :: Linux
Classifier: Topic :: Terminals :: Terminal Emulators/X Terminals
Requires-Python: >=3
License-File: LICENSE
Requires-Dist: volume-control
Requires-Dist: pynotification
Requires-Dist: pywifi-controls
Requires-Dist: block-stdout
Requires-Dist: pybrightness
Requires-Dist: pywslocker
